{
	"multipart": [
		{
			"apply": { "model": "crossroads:block/conduit/fluid_tube_core" }
		},

		{   "when": { "up": "input", "redstone_bool": "true" },
			"apply": { "model": "crossroads:block/conduit/alch_tube_cryst_in" }
		},
		{   "when": { "up": "output", "redstone_bool": "true" },
			"apply": { "model": "crossroads:block/conduit/alch_tube_cryst_out" }
		},

		{   "when": { "down": "input", "redstone_bool": "true" },
			"apply": { "model": "crossroads:block/conduit/alch_tube_cryst_in", "x": 180, "y": 0 }
		},
		{   "when": { "down": "output", "redstone_bool": "true" },
			"apply": { "model": "crossroads:block/conduit/alch_tube_cryst_out", "x": 180, "y": 0 }
		},

		{   "when": { "east": "input", "redstone_bool": "true" },
			"apply": { "model": "crossroads:block/conduit/alch_tube_cryst_in", "x": 90, "y": 90 }
		},
		{   "when": { "east": "output", "redstone_bool": "true" },
			"apply": { "model": "crossroads:block/conduit/alch_tube_cryst_out", "x": 90, "y": 90 }
		},

		{   "when": { "west": "input", "redstone_bool": "true" },
			"apply": { "model": "crossroads:block/conduit/alch_tube_cryst_in", "x": 90, "y": 270 }
		},
		{   "when": { "west": "output", "redstone_bool": "true" },
			"apply": { "model": "crossroads:block/conduit/alch_tube_cryst_out", "x": 90, "y": 270 }
		},

		{   "when": { "north": "input", "redstone_bool": "true" },
			"apply": { "model": "crossroads:block/conduit/alch_tube_cryst_in", "x": 90, "y": 0 }
		},
		{   "when": { "north": "output", "redstone_bool": "true" },
			"apply": { "model": "crossroads:block/conduit/alch_tube_cryst_out", "x": 90, "y": 0 }
		},

		{   "when": { "south": "input", "redstone_bool": "true" },
			"apply": { "model": "crossroads:block/conduit/alch_tube_cryst_in", "x": 90, "y": 180 }
		},
		{   "when": { "south": "output", "redstone_bool": "true" },
			"apply": { "model": "crossroads:block/conduit/alch_tube_cryst_out", "x": 90, "y": 180 }
		}
	]
}
